galaxy/__init__.py
galaxy/py.typed
galaxy/version.py
galaxy/exceptions/__init__.py
galaxy/exceptions/error_codes.json
galaxy/exceptions/error_codes.py
galaxy/exceptions/utils.py
galaxy/util/__init__.py
galaxy/util/aliaspickler.py
galaxy/util/bool_expressions.py
galaxy/util/bunch.py
galaxy/util/bytesize.py
galaxy/util/checkers.py
galaxy/util/commands.py
galaxy/util/compression_utils.py
galaxy/util/config_parsers.py
galaxy/util/config_templates.py
galaxy/util/dictifiable.py
galaxy/util/docutils_template.txt
galaxy/util/dynamic.py
galaxy/util/expressions.py
galaxy/util/facts.py
galaxy/util/filelock.py
galaxy/util/form_builder.py
galaxy/util/hash_util.py
galaxy/util/heartbeat.py
galaxy/util/image_util.py
galaxy/util/inflection.py
galaxy/util/json.py
galaxy/util/jstree.py
galaxy/util/lazy_process.py
galaxy/util/markdown.py
galaxy/util/monitors.py
galaxy/util/odict.py
galaxy/util/oset.py
galaxy/util/permutations.py
galaxy/util/plugin_config.py
galaxy/util/properties.py
galaxy/util/renamed_temporary_file.py
galaxy/util/requests.py
galaxy/util/resources.py
galaxy/util/rst_to_html.py
galaxy/util/rules_dsl.py
galaxy/util/rules_dsl_spec.yml
galaxy/util/sanitize_html.py
galaxy/util/script.py
galaxy/util/search.py
galaxy/util/simplegraph.py
galaxy/util/sleeper.py
galaxy/util/sockets.py
galaxy/util/specs.py
galaxy/util/sqlite.py
galaxy/util/submodules.py
galaxy/util/task.py
galaxy/util/template.py
galaxy/util/themes.py
galaxy/util/tool_version.py
galaxy/util/topsort.py
galaxy/util/tree_dict.py
galaxy/util/ucsc.py
galaxy/util/unittest.py
galaxy/util/user_agent.py
galaxy/util/validation.py
galaxy/util/watcher.py
galaxy/util/xml_macros.py
galaxy/util/yaml_util.py
galaxy/util/zipstream.py
galaxy/util/custom_logging/__init__.py
galaxy/util/custom_logging/fluent_log.py
galaxy/util/path/__init__.py
galaxy/util/path/ntpath.py
galaxy/util/path/posixpath.py
galaxy/util/tool_shed/__init__.py
galaxy/util/tool_shed/common_util.py
galaxy/util/tool_shed/encoding_util.py
galaxy_util-25.0.3.dist-info/licenses/LICENSE
galaxy_util-25.0.3.dist-info/METADATA
galaxy_util-25.0.3.dist-info/WHEEL
galaxy_util-25.0.3.dist-info/top_level.txt
galaxy_util-25.0.3.dist-info/RECORD
