Metadata-Version: 2.4
Name: galaxy-util
Version: 25.0.3
Summary: Galaxy generic utilities
Home-page: https://github.com/galaxyproject/galaxy
Author: Galaxy Project and Community
Author-email: galaxy-committers@lists.galaxyproject.org
License: AFL
Keywords: Galaxy
Classifier: Development Status :: 5 - Production/Stable
Classifier: Environment :: Console
Classifier: Intended Audience :: Developers
Classifier: License :: OSI Approved :: Academic Free License (AFL)
Classifier: Natural Language :: English
Classifier: Operating System :: POSIX
Classifier: Programming Language :: Python :: 3
Classifier: Programming Language :: Python :: 3.8
Classifier: Programming Language :: Python :: 3.9
Classifier: Programming Language :: Python :: 3.10
Classifier: Programming Language :: Python :: 3.11
Classifier: Programming Language :: Python :: 3.12
Classifier: Programming Language :: Python :: 3.13
Classifier: Topic :: Software Development
Classifier: Topic :: Software Development :: Code Generators
Classifier: Topic :: Software Development :: Testing
Requires-Python: >=3.8
License-File: LICENSE
Requires-Dist: bleach
Requires-Dist: boltons
Requires-Dist: docutils!=0.17,!=0.17.1
Requires-Dist: importlib-resources>=5.10.0; python_version < "3.12"
Requires-Dist: packaging
Requires-Dist: pyparsing
Requires-Dist: PyYAML
Requires-Dist: requests
Requires-Dist: Routes
Requires-Dist: typing-extensions
Requires-Dist: zipstream-new
Provides-Extra: image-util
Requires-Dist: pillow; extra == "image-util"
Provides-Extra: jstree
Requires-Dist: dictobj; extra == "jstree"
Provides-Extra: template
Requires-Dist: CT3>=3.3.3; extra == "template"
Requires-Dist: fissix; python_version >= "3.13" and extra == "template"
Requires-Dist: future>=1.0.0; extra == "template"
Provides-Extra: config-template
Requires-Dist: Jinja2; extra == "config-template"
Requires-Dist: pydantic; extra == "config-template"
Dynamic: license-file
